neuraltoolkit/__init__.py
neuraltoolkit/_version.py
neuraltoolkit/load_intan_rhd_format_hlab.py
neuraltoolkit/ntk_channelmap.py
neuraltoolkit/ntk_data_fields.py
neuraltoolkit/ntk_dlc.py
neuraltoolkit/ntk_ecube.py
neuraltoolkit/ntk_filters.py
neuraltoolkit/ntk_highd_data.py
neuraltoolkit/ntk_intan.py
neuraltoolkit/ntk_maths.py
neuraltoolkit/ntk_plots.py
neuraltoolkit/ntk_preprocess.py
neuraltoolkit/ntk_spikes.py
neuraltoolkit/ntk_stats.py
neuraltoolkit/ntk_sync.py
neuraltoolkit/ntk_utils.py
neuraltoolkit/ntk_videos.py
neuraltoolkit-0.4.2.dist-info/LICENSE
neuraltoolkit-0.4.2.dist-info/METADATA
neuraltoolkit-0.4.2.dist-info/WHEEL
neuraltoolkit-0.4.2.dist-info/top_level.txt
neuraltoolkit-0.4.2.dist-info/RECORD
