Metadata-Version: 2.1
Name: neuraltoolkit
Version: 0.4.2
Summary: A powerful and fast set of tools for loading data, filtering,                processing, working with data formats, and basic utilities for                electrophysiology and behavioral data.
Home-page: https://github.com/hengenlab/neuraltoolkit
Download-URL: https://github.com/hengenlab/neuraltoolkit
Author: (Hengen Lab Washington University in St. Louis)
Author-email: 
Maintainer: Kiran Bhaskaran-Nair,           (Hengen Lab Washington University in St. Louis)
Maintainer-email: 
Keywords: neuraltoolkit,neuroscience,electrophysiology
Classifier: Natural Language :: English
Classifier: Programming Language :: Python :: 3
License-File: LICENSE
Requires-Dist: ipython
Requires-Dist: numpy
Requires-Dist: matplotlib
Requires-Dist: seaborn
Requires-Dist: pandas
Requires-Dist: opencv-python
Requires-Dist: scipy
Requires-Dist: h5py
Requires-Dist: tables
Requires-Dist: requests
Provides-Extra: full
Requires-Dist: rpy2; extra == "full"
